sopel/__init__.py
sopel/bot.py
sopel/coretasks.py
sopel/db.py
sopel/formatting.py
sopel/lifecycle.py
sopel/loader.py
sopel/logger.py
sopel/module.py
sopel/plugin.py
sopel/privileges.py
sopel/trigger.py
sopel/builtins/__init__.py
sopel/builtins/admin.py
sopel/builtins/adminchannel.py
sopel/builtins/announce.py
sopel/builtins/calc.py
sopel/builtins/choose.py
sopel/builtins/clock.py
sopel/builtins/countdown.py
sopel/builtins/currency.py
sopel/builtins/dice.py
sopel/builtins/emoticons.py
sopel/builtins/find.py
sopel/builtins/find_updates.py
sopel/builtins/help.py
sopel/builtins/invite.py
sopel/builtins/isup.py
sopel/builtins/lmgtfy.py
sopel/builtins/ping.py
sopel/builtins/pronouns.py
sopel/builtins/rand.py
sopel/builtins/reload.py
sopel/builtins/safety.py
sopel/builtins/search.py
sopel/builtins/seen.py
sopel/builtins/tell.py
sopel/builtins/tld.py
sopel/builtins/translate.py
sopel/builtins/unicode_info.py
sopel/builtins/units.py
sopel/builtins/uptime.py
sopel/builtins/url.py
sopel/builtins/version.py
sopel/builtins/wikipedia.py
sopel/builtins/wiktionary.py
sopel/builtins/xkcd.py
sopel/cli/__init__.py
sopel/cli/config.py
sopel/cli/plugins.py
sopel/cli/run.py
sopel/cli/utils.py
sopel/config/__init__.py
sopel/config/core_section.py
sopel/config/types.py
sopel/irc/__init__.py
sopel/irc/abstract_backends.py
sopel/irc/backends.py
sopel/irc/capabilities.py
sopel/irc/isupport.py
sopel/irc/modes.py
sopel/irc/utils.py
sopel/plugins/__init__.py
sopel/plugins/capabilities.py
sopel/plugins/exceptions.py
sopel/plugins/handlers.py
sopel/plugins/jobs.py
sopel/plugins/rules.py
sopel/tests/__init__.py
sopel/tests/factories.py
sopel/tests/mocks.py
sopel/tests/pytest_plugin.py
sopel/tools/__init__.py
sopel/tools/_events.py
sopel/tools/calculation.py
sopel/tools/identifiers.py
sopel/tools/jobs.py
sopel/tools/memories.py
sopel/tools/target.py
sopel/tools/time.py
sopel/tools/web.py
sopel-8.0.4.dist-info/METADATA
sopel-8.0.4.dist-info/WHEEL
sopel-8.0.4.dist-info/entry_points.txt
sopel-8.0.4.dist-info/top_level.txt
sopel-8.0.4.dist-info/RECORD
