Metadata-Version: 2.1
Name: sopel
Version: 8.0.4
Summary: Simple and extensible IRC bot
Author: dgw, Florian Strzelecki, Sean B. Palmer, Else Powell, Elad Alfassa, Dimitri Molenaars, Michael Yanovich
Maintainer: dgw, Florian Strzelecki
License: EFL-2.0
Project-URL: Homepage, https://sopel.chat/
Project-URL: Release notes, https://sopel.chat/changelog/
Project-URL: Documentation, https://sopel.chat/docs/
Project-URL: Bug Tracker, https://github.com/sopel-irc/sopel/issues
Project-URL: Donate on Open Collective, https://opencollective.com/sopel
Project-URL: Donate on GitHub, https://github.com/sponsors/sopel-irc
Project-URL: Source, https://github.com/sopel-irc/sopel
Project-URL: Coverage, https://coveralls.io/github/sopel-irc/sopel
Platform: Linux x86, x86-64
Classifier: Development Status :: 5 - Production/Stable
Classifier: Intended Audience :: Developers
Classifier: Intended Audience :: System Administrators
Classifier: License :: Eiffel Forum License (EFL)
Classifier: License :: OSI Approved :: Eiffel Forum License
Classifier: Operating System :: POSIX :: Linux
Classifier: Programming Language :: Python :: 3.8
Classifier: Programming Language :: Python :: 3.9
Classifier: Programming Language :: Python :: 3.10
Classifier: Programming Language :: Python :: 3.11
Classifier: Programming Language :: Python :: 3.12
Classifier: Topic :: Communications :: Chat :: Internet Relay Chat
Requires-Python: >=3.8
Requires-Dist: xmltodict<0.14,>=0.12
Requires-Dist: pytz
Requires-Dist: requests<3.0.0,>=2.24.0
Requires-Dist: dnspython<3.0
Requires-Dist: sqlalchemy<1.5,>=1.4
Requires-Dist: importlib-metadata>=3.6
Requires-Dist: packaging>=23.2
Requires-Dist: sopel-help>=0.4.0
Requires-Dist: typing-extensions>=4.4
